mt_ODBC/MaxTrack.py
mt_ODBC/MaxTrack1.py
mt_ODBC/__init__.py
mt_ODBC/mt_FileMan.py
mt_ODBC/mt_ODBC.py
mt_ODBC/test.py
mt_ODBC/test2.py
mt_ODBC-0.0.5.dist-info/LICENSE
mt_ODBC-0.0.5.dist-info/METADATA
mt_ODBC-0.0.5.dist-info/WHEEL
mt_ODBC-0.0.5.dist-info/top_level.txt
mt_ODBC-0.0.5.dist-info/RECORD
