Metadata-Version: 2.1
Name: mt-ODBC
Version: 0.0.5
Summary: A package for custom ODBC wrappers and methods for MaxTrack
Home-page: UNKNOWN
Author: mole1000
Author-email: mole1000@protonmail.com
License: UNKNOWN
Platform: UNKNOWN
Classifier: Programming Language :: Python :: 3
Classifier: License :: OSI Approved :: MIT License
Classifier: Operating System :: OS Independent
Requires-Python: >=3.6
Requires-Dist: pyodbc (>=4.0)
Provides-Extra: testing
Requires-Dist: pytest ; extra == 'testing'
